py_gasbuddy/__init__.py
py_gasbuddy/cache.py
py_gasbuddy/consts.py
py_gasbuddy/exceptions.py
py_gasbuddy-0.4.2.dist-info/licenses/LICENSE
py_gasbuddy-0.4.2.dist-info/METADATA
py_gasbuddy-0.4.2.dist-info/WHEEL
py_gasbuddy-0.4.2.dist-info/top_level.txt
py_gasbuddy-0.4.2.dist-info/RECORD
