Metadata-Version: 2.4
Name: py_gasbuddy
Version: 0.4.2
Summary: Python wrapper for GasBuddy GraphQL API
Home-page: https://github.com/firstof9/py-gasbuddy
Download-URL: https://github.com/firstof9/py-gasbuddy
Author: firstof9
Author-email: firstof9@gmail.com
Classifier: Development Status :: 4 - Beta
Classifier: Intended Audience :: Developers
Classifier: Natural Language :: English
Classifier: Programming Language :: Python :: 3
Classifier: Programming Language :: Python :: 3.12
Classifier: Programming Language :: Python :: 3.13
Requires-Python: >=3.10
License-File: LICENSE
Requires-Dist: aiohttp
Requires-Dist: requests
Dynamic: author
Dynamic: author-email
Dynamic: classifier
Dynamic: description
Dynamic: description-content-type
Dynamic: download-url
Dynamic: home-page
Dynamic: license-file
Dynamic: requires-dist
Dynamic: requires-python
Dynamic: summary
